rsi_data/__init__.py
rsi_data/quickpulse/__init__.py
rsi_data/quickpulse/_http.py
rsi_data/quickpulse/_sse.py
rsi_data/quickpulse/_utils.py
rsi_data/quickpulse/async_client.py
rsi_data/quickpulse/client.py
rsi_data/quickpulse/errors.py
rsi_data/quickpulse/models.py
rsi_data/quickpulse/research.py
rsi_data_quickpulse-0.1.1.dist-info/METADATA
rsi_data_quickpulse-0.1.1.dist-info/WHEEL
rsi_data_quickpulse-0.1.1.dist-info/licenses/LICENSE
rsi_data_quickpulse-0.1.1.dist-info/RECORD
