Metadata-Version: 2.4
Name: rsi-data-quickpulse
Version: 0.1.1
Summary: QuickPulse Python SDK for Research API (sync + async)
Project-URL: Homepage, https://api.rsi-data.com
Project-URL: Repository, https://github.com/neon-nerd-herd/rsi_data_sdk.git
Author-email: RSI Data <support@rsi-data.com>
License: MIT License
License-File: LICENSE
Keywords: httpx,quickpulse,research,sdk,sse
Classifier: Intended Audience :: Developers
Classifier: License :: OSI Approved :: MIT License
Classifier: Programming Language :: Python :: 3
Classifier: Programming Language :: Python :: 3 :: Only
Classifier: Programming Language :: Python :: 3.8
Classifier: Programming Language :: Python :: 3.9
Classifier: Programming Language :: Python :: 3.10
Classifier: Programming Language :: Python :: 3.11
Classifier: Programming Language :: Python :: 3.12
Classifier: Topic :: Internet :: WWW/HTTP
Classifier: Topic :: Software Development :: Libraries :: Python Modules
Requires-Python: >=3.8
Requires-Dist: httpx>=0.27
Requires-Dist: typing-extensions>=4.0; python_version < '3.11'
